PredictDSSP/.DS_Store
PredictDSSP/__init__.py
PredictDSSP/_version.py
PredictDSSP/brnn_architecture.py
PredictDSSP/dssp.py
PredictDSSP/dssp_exceptions.py
PredictDSSP/dssp_graph.py
PredictDSSP/dssp_predict.py
PredictDSSP/dssp_tools.py
PredictDSSP/encode_sequence.py
PredictDSSP/py_predictor_v2.py
PredictDSSP/uniprot_predictions.py
PredictDSSP/data/README.md
PredictDSSP/data/look_and_say.dat
PredictDSSP/networks/.DS_Store
PredictDSSP/networks/dssp_2022_01_07_CB_thresh_0p8_hs20_nl2.pt
PredictDSSP/scripts/__init__.py
PredictDSSP/scripts/dssp_fasta.py
PredictDSSP/scripts/dssp_name.py
PredictDSSP/scripts/dssp_uniprot.py
PredictDSSP/tests/__init__.py
PredictDSSP/tests/test_PredictDSSP.py
PredictDSSP-1.3.1.dist-info/LICENSE
PredictDSSP-1.3.1.dist-info/METADATA
PredictDSSP-1.3.1.dist-info/WHEEL
PredictDSSP-1.3.1.dist-info/entry_points.txt
PredictDSSP-1.3.1.dist-info/top_level.txt
PredictDSSP-1.3.1.dist-info/RECORD
