Metadata-Version: 2.1
Name: PredictDSSP
Version: 1.3.1
Summary: Python package that predicts secondary structure (DSSP) scores using a BRRN classifier
Author-email: Ryan Emenecker <remenecker@wustl.edu>
License: MIT
Requires-Python: >=3.8
License-File: LICENSE
Requires-Dist: numpy
Requires-Dist: torch
Requires-Dist: metapredict >=2.65.1
Requires-Dist: matplotlib
Requires-Dist: protfasta >=0.1.15.2
Requires-Dist: urllib3
Requires-Dist: alphaPredict
Requires-Dist: getSequence >=1.3
Requires-Dist: requests
Provides-Extra: test
Requires-Dist: pytest >=6.1.2 ; extra == 'test'
